initgitdoc-0.3.6.data/scripts/docgitinit.py
initgitdoc-0.3.6.data/scripts/initgitdoc
initgitdoc-0.3.6.data/scripts/templates.py
initgitdoc-0.3.6.data/scripts/updatereadmescripts
templates/__init__.py
templates/bug_report.py
templates/conduct.py
templates/contrib.py
templates/feature_requests.py
templates/funding.py
templates/gitignore.py
templates/issues.py
templates/licences.py
templates/pull_requests.py
templates/readme.py
templates/workflows.py
initgitdoc-0.3.6.dist-info/LICENSE
initgitdoc-0.3.6.dist-info/METADATA
initgitdoc-0.3.6.dist-info/WHEEL
initgitdoc-0.3.6.dist-info/top_level.txt
initgitdoc-0.3.6.dist-info/RECORD
