Metadata-Version: 2.1
Name: initgitdoc
Version: 0.3.6
Summary: A utility to generate common git repository files, Readmes,Licenses,..etc.
Home-page: https://github.com/TralahM/docrepo
Author: Tralah M Brian
Author-email: musyoki.brian@tralahtek.com
License: UNKNOWN
Platform: UNKNOWN
Classifier: Programming Language :: Python
Classifier: Programming Language :: Python :: 3
Classifier: License :: OSI Approved :: MIT License
Classifier: Operating System :: OS Independent
